g4l/__init__.py
g4l/g4l.py
g4l-0.1.4.dist-info/LICENSE
g4l-0.1.4.dist-info/METADATA
g4l-0.1.4.dist-info/WHEEL
g4l-0.1.4.dist-info/top_level.txt
g4l-0.1.4.dist-info/RECORD
