Metadata-Version: 2.1
Name: g4l
Version: 0.1.4
Summary: gpio for linux
Home-page: https://gitlab.com/telelian/peripheral-library/g4l.git
Author: mrzjo
Author-email: mrzjo05@gmail.com
Classifier: Development Status :: 4 - Beta
Classifier: Programming Language :: Python
Classifier: Programming Language :: Python :: 3
Classifier: Programming Language :: Python :: 3.4
Classifier: Programming Language :: Python :: 3.5
Classifier: Programming Language :: Python :: 3.7
Classifier: Programming Language :: Python :: 3.9
Classifier: Topic :: System :: Hardware
License-File: LICENSE
